scrapy_magicfields/__init__.py
scrapy_magicfields/middleware.py
scrapy_magicfields-1.1.0.dist-info/DESCRIPTION.rst
scrapy_magicfields-1.1.0.dist-info/METADATA
scrapy_magicfields-1.1.0.dist-info/RECORD
scrapy_magicfields-1.1.0.dist-info/WHEEL
scrapy_magicfields-1.1.0.dist-info/metadata.json
scrapy_magicfields-1.1.0.dist-info/top_level.txt
