Metadata-Version: 2.0
Name: scrapy-magicfields
Version: 1.1.0
Summary: Scrapy middleware to add extra "magic" fields to items
Home-page: http://github.com/scrapy-plugins/scrapy-magicfields
Author: Scrapinghub
Author-email: info@scrapinghub.com
License: BSD
Platform: Any
Classifier: Development Status :: 4 - Beta
Classifier: License :: OSI Approved :: BSD License
Classifier: Operating System :: OS Independent
Classifier: Programming Language :: Python
Classifier: Programming Language :: Python :: 2
Classifier: Programming Language :: Python :: 2.7
Classifier: Programming Language :: Python :: 3
Classifier: Programming Language :: Python :: 3.5
Requires-Dist: scrapy
